.gitignore
PKG-INFO
README.md
pyproject.toml
bec_server/__init__.py
bec_server/bec_server_utils/__init__.py
bec_server/bec_server_utils/launch.py
bec_server/bec_server_utils/service_handler.py
bec_server/bec_server_utils/subprocess_launch.py
bec_server/bec_server_utils/tmux_launch.py
bec_server/data_processing/__init__.py
bec_server/data_processing/dap_server.py
bec_server/data_processing/dap_service.py
bec_server/data_processing/dap_service_manager.py
bec_server/data_processing/image_analysis_service.py
bec_server/data_processing/lmfit1d_service.py
bec_server/data_processing/cli/__init__.py
bec_server/data_processing/cli/launch.py
bec_server/device_server/__init__.py
bec_server/device_server/bec_message_handler.py
bec_server/device_server/device_server.py
bec_server/device_server/rpc_handler.py
bec_server/device_server/cli/__init__.py
bec_server/device_server/cli/launch.py
bec_server/device_server/devices/__init__.py
bec_server/device_server/devices/config_update_handler.py
bec_server/device_server/devices/device_serializer.py
bec_server/device_server/devices/devicemanager.py
bec_server/device_server/tests/__init__.py
bec_server/device_server/tests/utils.py
bec_server/file_writer/__init__.py
bec_server/file_writer/async_writer.py
bec_server/file_writer/default_writer.py
bec_server/file_writer/file_writer.py
bec_server/file_writer/file_writer_manager.py
bec_server/file_writer/merged_dicts.py
bec_server/file_writer/cli/__init__.py
bec_server/file_writer/cli/launch.py
bec_server/file_writer_plugins/__init__.py
bec_server/file_writer_plugins/cSAXS.py
bec_server/procedures/Containerfile.bec_linux_base
bec_server/procedures/Containerfile.requirements
bec_server/procedures/Containerfile.worker
bec_server/procedures/__init__.py
bec_server/procedures/_dev_runner.py
bec_server/procedures/builtin_procedures.py
bec_server/procedures/constants.py
bec_server/procedures/container_utils.py
bec_server/procedures/container_worker.py
bec_server/procedures/manager.py
bec_server-3.94.0.dist-info/METADATA
bec_server-3.94.0.dist-info/WHEEL
bec_server-3.94.0.dist-info/entry_points.txt
bec_server-3.94.0.dist-info/RECORD
