Metadata-Version: 2.4
Name: bec-server
Version: 3.94.0
Summary: BEC server
Project-URL: Bug Tracker, https://github.com/bec-project/bec/issues
Project-URL: Homepage, https://github.com/bec-project/bec
Classifier: Development Status :: 3 - Alpha
Classifier: Programming Language :: Python :: 3
Classifier: Topic :: Scientific/Engineering
Requires-Python: >=3.11
Requires-Dist: bec-lib~=3.0
Requires-Dist: h5py~=3.10
Requires-Dist: libtmux~=0.37
Requires-Dist: lmfit~=1.3
Requires-Dist: msgpack~=1.0
Requires-Dist: numpy<3.0,>=1.24
Requires-Dist: ophyd-devices<2.0,>=1.29.7
Requires-Dist: ophyd~=1.9
Requires-Dist: podman>=5.4
Requires-Dist: psutil
Requires-Dist: pydantic~=2.8
Requires-Dist: python-dotenv~=1.0
Requires-Dist: pyyaml~=6.0
Requires-Dist: rich~=13.7
Provides-Extra: dev
Requires-Dist: black~=25.0; extra == 'dev'
Requires-Dist: coverage~=7.0; extra == 'dev'
Requires-Dist: fakeredis>=2.23.2,~=2.23; extra == 'dev'
Requires-Dist: isort>=5.13.2,~=5.13; extra == 'dev'
Requires-Dist: pylint~=3.0; extra == 'dev'
Requires-Dist: pytest-random-order~=1.1; extra == 'dev'
Requires-Dist: pytest-timeout~=2.2; extra == 'dev'
Requires-Dist: pytest~=8.0; extra == 'dev'
